{"municipality": "Oslo", "municipalityNumber": "0301", "station": "Hjortnes", "components": [{"component": "PM10", "unit": "\u00b5g/m\u00b3", "values": [{"year": 2012, "validHours": 8769.0, "aggregated": 187049.5600000002, "value": 21.330774318622442, "isValid": true, "aboveLowerThreshold": true, "aboveUpperThreshold": false, "aboveBoundary": false, "dailyLowerCount": 95, "dailyUpperCount": 56, "dailyBoundaryCount": 22}, {"year": 2013, "validHours": 8627.0, "aggregated": 236983.11000000095, "value": 27.469932769213045, "isValid": true, "aboveLowerThreshold": true, "aboveUpperThreshold": false, "aboveBoundary": false, "dailyLowerCount": 129, "dailyUpperCount": 79, "dailyBoundaryCount": 44}, {"year": 2014, "validHours": 8626.0, "aggregated": 211823.48000000048, "value": 24.55639693948533, "isValid": true, "aboveLowerThreshold": true, "aboveUpperThreshold": false, "aboveBoundary": false, "dailyLowerCount": 116, "dailyUpperCount": 56, "dailyBoundaryCount": 21}, {"year": 2015, "validHours": 8670.0, "aggregated": 206381.78000000052, "value": 23.804126874279184, "isValid": true, "aboveLowerThreshold": true, "aboveUpperThreshold": false, "aboveBoundary": false, "dailyLowerCount": 106, "dailyUpperCount": 59, "dailyBoundaryCount": 26}, {"year": 2016, "validHours": 8729.0, "aggregated": 209359.26, "value": 23.98433497536946, "isValid": true, "aboveLowerThreshold": true, "aboveUpperThreshold": true, "aboveBoundary": false, "dailyLowerCount": 103, "dailyUpperCount": 62, "dailyBoundaryCount": 25}, {"year": 2017, "validHours": 8676.0, "aggregated": 193320.26999999964, "value": 22.282188796680458, "isValid": true, "aboveLowerThreshold": true, "aboveUpperThreshold": false, "aboveBoundary": false, "dailyLowerCount": 98, "dailyUpperCount": 50, "dailyBoundaryCount": 18}, {"year": 2018, "validHours": 8690.0, "aggregated": 210229.69, "value": 24.19213924050633, "isValid": true, "aboveLowerThreshold": true, "aboveUpperThreshold": true, "aboveBoundary": false, "dailyLowerCount": 122, "dailyUpperCount": 58, "dailyBoundaryCount": 18}, {"year": 2019, "validHours": 8686.0, "aggregated": 191348.95999999958, "value": 22.02958323739346, "isValid": true, "aboveLowerThreshold": true, "aboveUpperThreshold": false, "aboveBoundary": false, "dailyLowerCount": 91, "dailyUpperCount": 53, "dailyBoundaryCount": 20}, {"year": 2020, "validHours": 8520.0, "aggregated": 170556.09999999986, "value": 20.018321596244114, "isValid": true, "aboveLowerThreshold": false, "aboveUpperThreshold": false, "aboveBoundary": false, "dailyLowerCount": 64, "dailyUpperCount": 37, "dailyBoundaryCount": 22}, {"year": 2021, "validHours": 8550.0, "aggregated": 208482.07999999987, "value": 24.383869005847938, "isValid": true, "aboveLowerThreshold": true, "aboveUpperThreshold": true, "aboveBoundary": false, "dailyLowerCount": 112, "dailyUpperCount": 62, "dailyBoundaryCount": 29}, {"year": 2022, "validHours": 8692.0, "aggregated": 205132.29999999944, "value": 23.600126553152258, "isValid": true, "aboveLowerThreshold": true, "aboveUpperThreshold": true, "aboveBoundary": true, "dailyLowerCount": 101, "dailyUpperCount": 64, "dailyBoundaryCount": 32}]}, {"component": "PM2.5", "unit": "\u00b5g/m\u00b3", "values": [{"year": 2012, "validHours": 8728.0, "aggregated": 76732.40999999993, "value": 8.791522685609525, "isValid": true, "aboveLowerThreshold": false, "aboveUpperThreshold": false, "aboveBoundary": false}, {"year": 2013, "validHours": 8650.0, "aggregated": 81289.91999999985, "value": 9.397678612716746, "isValid": true, "aboveLowerThreshold": false, "aboveUpperThreshold": false, "aboveBoundary": false}, {"year": 2014, "validHours": 8723.0, "aggregated": 84880.5000000001, "value": 9.73065459131034, "isValid": true, "aboveLowerThreshold": false, "aboveUpperThreshold": false, "aboveBoundary": false}, {"year": 2015, "validHours": 8716.0, "aggregated": 74476.7999999999, "value": 8.544837081229911, "isValid": true, "aboveLowerThreshold": false, "aboveUpperThreshold": false, "aboveBoundary": false}, {"year": 2016, "validHours": 8716.0, "aggregated": 77234.49999999978, "value": 8.8612322166131, "isValid": true, "aboveLowerThreshold": false, "aboveUpperThreshold": false, "aboveBoundary": false}, {"year": 2017, "validHours": 8686.0, "aggregated": 72406.90000000014, "value": 8.336046511627924, "isValid": true, "aboveLowerThreshold": false, "aboveUpperThreshold": false, "aboveBoundary": false}, {"year": 2018, "validHours": 8428.0, "aggregated": 73865.70000000007, "value": 8.764321309919325, "isValid": true, "aboveLowerThreshold": false, "aboveUpperThreshold": false, "aboveBoundary": false}, {"year": 2019, "validHours": 8695.0, "aggregated": 77437.39999999964, "value": 8.905968947671035, "isValid": true, "aboveLowerThreshold": false, "aboveUpperThreshold": false, "aboveBoundary": false}, {"year": 2020, "validHours": 8550.0, "aggregated": 58777.59999999988, "value": 6.874573099415191, "isValid": true, "aboveLowerThreshold": false, "aboveUpperThreshold": false, "aboveBoundary": false}, {"year": 2021, "validHours": 8651.0, "aggregated": 68819.4999999996, "value": 7.955091896890488, "isValid": true, "aboveLowerThreshold": false, "aboveUpperThreshold": false, "aboveBoundary": false}, {"year": 2022, "validHours": 8365.0, "aggregated": 63269.000000000044, "value": 7.563538553496718, "isValid": true, "aboveLowerThreshold": true, "aboveUpperThreshold": true, "aboveBoundary": false}]}, {"component": "NO2", "unit": "\u00b5g/m\u00b3", "values": [{"year": 2012, "validHours": 8203.0, "aggregated": 385724.5599999985, "value": 47.02237717908064, "isValid": true, "aboveLowerThreshold": true, "aboveUpperThreshold": true, "aboveBoundary": true, "hourlyLowerCount": 791, "hourlyUpperCount": 208, "hourlyBoundaryCount": 25}, {"year": 2013, "validHours": 8435.0, "aggregated": 424102.24188599974, "value": 50.27886685074093, "isValid": true, "aboveLowerThreshold": true, "aboveUpperThreshold": true, "aboveBoundary": true, "hourlyLowerCount": 980, "hourlyUpperCount": 268, "hourlyBoundaryCount": 16}, {"year": 2014, "validHours": 7710.0, "aggregated": 355607.5268880011, "value": 46.1228958350196, "isValid": true, "aboveLowerThreshold": true, "aboveUpperThreshold": true, "aboveBoundary": true, "hourlyLowerCount": 677, "hourlyUpperCount": 129, "hourlyBoundaryCount": 0}, {"year": 2015, "validHours": 8704.0, "aggregated": 385821.3605529987, "value": 44.32690263706327, "isValid": true, "aboveLowerThreshold": true, "aboveUpperThreshold": true, "aboveBoundary": true, "hourlyLowerCount": 858, "hourlyUpperCount": 205, "hourlyBoundaryCount": 23}, {"year": 2016, "validHours": 8484.0, "aggregated": 389083.0703980013, "value": 45.86080509170218, "isValid": true, "aboveLowerThreshold": true, "aboveUpperThreshold": true, "aboveBoundary": true, "hourlyLowerCount": 748, "hourlyUpperCount": 193, "hourlyBoundaryCount": 30}, {"year": 2017, "validHours": 8715.0, "aggregated": 356919.6571639993, "value": 40.95463650763044, "isValid": true, "aboveLowerThreshold": true, "aboveUpperThreshold": true, "aboveBoundary": true, "hourlyLowerCount": 487, "hourlyUpperCount": 80, "hourlyBoundaryCount": 0}, {"year": 2018, "validHours": 8710.0, "aggregated": 312339.25256400125, "value": 35.859845300114955, "isValid": true, "aboveLowerThreshold": true, "aboveUpperThreshold": true, "aboveBoundary": false, "hourlyLowerCount": 223, "hourlyUpperCount": 12, "hourlyBoundaryCount": 0}, {"year": 2019, "validHours": 8701.0, "aggregated": 305101.2410309992, "value": 35.06507769578201, "isValid": true, "aboveLowerThreshold": true, "aboveUpperThreshold": true, "aboveBoundary": false, "hourlyLowerCount": 250, "hourlyUpperCount": 10, "hourlyBoundaryCount": 0}, {"year": 2020, "validHours": 8514.0, "aggregated": 205376.43388899957, "value": 24.122202711886253, "isValid": true, "aboveLowerThreshold": false, "aboveUpperThreshold": false, "aboveBoundary": false, "hourlyLowerCount": 73, "hourlyUpperCount": 0, "hourlyBoundaryCount": 0}, {"year": 2021, "validHours": 8704.0, "aggregated": 233566.32427600064, "value": 26.834366300091986, "isValid": true, "aboveLowerThreshold": true, "aboveUpperThreshold": false, "aboveBoundary": false, "hourlyLowerCount": 30, "hourlyUpperCount": 0, "hourlyBoundaryCount": 0}, {"year": 2022, "validHours": 8688.0, "aggregated": 220472.18084700013, "value": 25.37663223377073, "isValid": true, "aboveLowerThreshold": false, "aboveUpperThreshold": false, "aboveBoundary": false, "hourlyLowerCount": 35, "hourlyUpperCount": 0, "hourlyBoundaryCount": 0}]}, {"component": "Benzoapyrene", "unit": "ng/m\u00b3", "values": [{"year": 2009, "qualityControlled": true, "value": 0.36, "isValid": true, "aboveLowerThreshold": false, "aboveUpperThreshold": false, "aboveBoundary": false}, {"year": 2010, "qualityControlled": true, "value": 0.54, "isValid": true, "aboveLowerThreshold": true, "aboveUpperThreshold": false, "aboveBoundary": false}, {"year": 2011, "qualityControlled": true, "value": 0.31, "isValid": true, "aboveLowerThreshold": false, "aboveUpperThreshold": false, "aboveBoundary": false}, {"year": 2012, "qualityControlled": true, "value": 0.19, "isValid": true, "aboveLowerThreshold": false, "aboveUpperThreshold": false, "aboveBoundary": false}, {"year": 2013, "qualityControlled": true, "value": 0.3, "isValid": true, "aboveLowerThreshold": false, "aboveUpperThreshold": false, "aboveBoundary": false}, {"year": 2014, "qualityControlled": true, "value": 0.34, "isValid": true, "aboveLowerThreshold": false, "aboveUpperThreshold": false, "aboveBoundary": false}, {"year": 2015, "qualityControlled": true, "value": 0.31, "isValid": true, "aboveLowerThreshold": false, "aboveUpperThreshold": false, "aboveBoundary": false}, {"year": 2016, "qualityControlled": true, "value": 0.45, "isValid": true, "aboveLowerThreshold": false, "aboveUpperThreshold": false, "aboveBoundary": false}, {"year": 2017, "qualityControlled": true, "value": 0.37, "isValid": true, "aboveLowerThreshold": false, "aboveUpperThreshold": false, "aboveBoundary": false}, {"year": 2018, "qualityControlled": true, "value": 0.28, "isValid": true, "aboveLowerThreshold": false, "aboveUpperThreshold": false, "aboveBoundary": false}, {"year": 2019, "qualityControlled": true, "value": 0.3, "isValid": true, "aboveLowerThreshold": false, "aboveUpperThreshold": false, "aboveBoundary": false}, {"year": 2020, "qualityControlled": true, "value": 0.2, "isValid": true, "aboveLowerThreshold": false, "aboveUpperThreshold": false, "aboveBoundary": false}, {"year": 2021, "qualityControlled": true, "value": 0.3, "isValid": true, "aboveLowerThreshold": false, "aboveUpperThreshold": false, "aboveBoundary": false}, {"year": 2022, "qualityControlled": true, "value": 0.4, "isValid": true, "aboveLowerThreshold": false, "aboveUpperThreshold": false, "aboveBoundary": false}]}]}