{"municipality": "Oslo", "municipalityNumber": "0301", "station": "Bryn skole", "components": [{"component": "PM2.5", "unit": "\u00b5g/m\u00b3", "values": [{"year": 2018, "validHours": 775.0, "aggregated": 9443.555543000004, "value": 12.185232958709683, "isValid": false, "aboveLowerThreshold": true, "aboveUpperThreshold": false, "aboveBoundary": false}, {"year": 2019, "validHours": 8413.0, "aggregated": 69619.97870200017, "value": 8.27528571282541, "isValid": true, "aboveLowerThreshold": false, "aboveUpperThreshold": false, "aboveBoundary": false}, {"year": 2020, "validHours": 7918.0, "aggregated": 54428.84276400027, "value": 6.874064506693643, "isValid": true, "aboveLowerThreshold": false, "aboveUpperThreshold": false, "aboveBoundary": false}, {"year": 2021, "validHours": 6012.0, "aggregated": 44972.67065099995, "value": 7.480484140219552, "isValid": false, "aboveLowerThreshold": false, "aboveUpperThreshold": false, "aboveBoundary": false}, {"year": 2022, "validHours": 7145.0, "aggregated": 53644.153141999974, "value": 7.507929061161648, "isValid": false, "aboveLowerThreshold": true, "aboveUpperThreshold": true, "aboveBoundary": false}]}, {"component": "NO2", "unit": "\u00b5g/m\u00b3", "values": [{"year": 2018, "validHours": 601.0, "aggregated": 20306.926741000003, "value": 33.78856362895175, "isValid": false, "aboveLowerThreshold": true, "aboveUpperThreshold": true, "aboveBoundary": false, "hourlyLowerCount": 0, "hourlyUpperCount": 0, "hourlyBoundaryCount": 0}, {"year": 2019, "validHours": 8163.0, "aggregated": 187568.11316399966, "value": 22.977840642410836, "isValid": true, "aboveLowerThreshold": false, "aboveUpperThreshold": false, "aboveBoundary": false, "hourlyLowerCount": 57, "hourlyUpperCount": 10, "hourlyBoundaryCount": 0}, {"year": 2020, "validHours": 8387.0, "aggregated": 143613.60513900052, "value": 17.12335818993687, "isValid": true, "aboveLowerThreshold": false, "aboveUpperThreshold": false, "aboveBoundary": false, "hourlyLowerCount": 6, "hourlyUpperCount": 3, "hourlyBoundaryCount": 0}, {"year": 2021, "validHours": 8383.0, "aggregated": 160936.73414300007, "value": 19.197988088154606, "isValid": true, "aboveLowerThreshold": false, "aboveUpperThreshold": false, "aboveBoundary": false, "hourlyLowerCount": 8, "hourlyUpperCount": 0, "hourlyBoundaryCount": 0}, {"year": 2022, "validHours": 8035.0, "aggregated": 143634.12246399984, "value": 17.876057556191643, "isValid": true, "aboveLowerThreshold": false, "aboveUpperThreshold": false, "aboveBoundary": false, "hourlyLowerCount": 4, "hourlyUpperCount": 0, "hourlyBoundaryCount": 0}]}, {"component": "PM10", "unit": "\u00b5g/m\u00b3", "values": [{"year": 2018, "validHours": 775.0, "aggregated": 11153.143211000011, "value": 14.391152530322595, "isValid": false, "aboveLowerThreshold": false, "aboveUpperThreshold": false, "aboveBoundary": false, "dailyLowerCount": 2, "dailyUpperCount": 0, "dailyBoundaryCount": 0}, {"year": 2019, "validHours": 8413.0, "aggregated": 116996.5471929997, "value": 13.90663820194933, "isValid": true, "aboveLowerThreshold": false, "aboveUpperThreshold": false, "aboveBoundary": false, "dailyLowerCount": 48, "dailyUpperCount": 19, "dailyBoundaryCount": 7}, {"year": 2020, "validHours": 7918.0, "aggregated": 121631.12951499979, "value": 15.361344975372543, "isValid": true, "aboveLowerThreshold": false, "aboveUpperThreshold": false, "aboveBoundary": false, "dailyLowerCount": 41, "dailyUpperCount": 26, "dailyBoundaryCount": 17}, {"year": 2021, "validHours": 6012.0, "aggregated": 79171.32914299998, "value": 13.168883756320689, "isValid": false, "aboveLowerThreshold": false, "aboveUpperThreshold": false, "aboveBoundary": false, "dailyLowerCount": 21, "dailyUpperCount": 8, "dailyBoundaryCount": 1}, {"year": 2022, "validHours": 7145.0, "aggregated": 109211.5010529999, "value": 15.285024640027977, "isValid": false, "aboveLowerThreshold": false, "aboveUpperThreshold": false, "aboveBoundary": false, "dailyLowerCount": 45, "dailyUpperCount": 25, "dailyBoundaryCount": 9}]}]}