{"municipality": "Trondheim", "municipalityNumber": "5001", "station": "Bakke kirke", "components": [{"component": "PM2.5", "unit": "\u00b5g/m\u00b3", "values": [{"year": 2012, "validHours": 8418.0, "aggregated": 69820.00000000004, "value": 8.29413162271324, "isValid": true, "aboveLowerThreshold": false, "aboveUpperThreshold": false, "aboveBoundary": false}, {"year": 2013, "validHours": 8449.0, "aggregated": 65893.8, "value": 7.7990057995029005, "isValid": true, "aboveLowerThreshold": false, "aboveUpperThreshold": false, "aboveBoundary": false}, {"year": 2014, "validHours": 7943.0, "aggregated": 59281.79942899996, "value": 7.463401665491623, "isValid": true, "aboveLowerThreshold": false, "aboveUpperThreshold": false, "aboveBoundary": false}, {"year": 2015, "validHours": 8305.0, "aggregated": 55687.02425900006, "value": 6.705240729560513, "isValid": true, "aboveLowerThreshold": false, "aboveUpperThreshold": false, "aboveBoundary": false}, {"year": 2016, "validHours": 8443.0, "aggregated": 49525.39994699987, "value": 5.865853363377931, "isValid": true, "aboveLowerThreshold": false, "aboveUpperThreshold": false, "aboveBoundary": false}, {"year": 2017, "validHours": 8397.0, "aggregated": 40897.87845199984, "value": 4.8705345304275145, "isValid": true, "aboveLowerThreshold": false, "aboveUpperThreshold": false, "aboveBoundary": false}, {"year": 2018, "validHours": 8485.0, "aggregated": 47154.0155530001, "value": 5.557338309133777, "isValid": true, "aboveLowerThreshold": false, "aboveUpperThreshold": false, "aboveBoundary": false}, {"year": 2019, "validHours": 7804.0, "aggregated": 39874.32786599992, "value": 5.109473073552015, "isValid": true, "aboveLowerThreshold": false, "aboveUpperThreshold": false, "aboveBoundary": false}, {"year": 2020, "validHours": 6698.0, "aggregated": 25573.355154000066, "value": 3.8180583986264653, "isValid": false, "aboveLowerThreshold": false, "aboveUpperThreshold": false, "aboveBoundary": false}]}, {"component": "NO2", "unit": "\u00b5g/m\u00b3", "values": [{"year": 2012, "validHours": 8705.0, "aggregated": 235616.1428600007, "value": 27.066759662263145, "isValid": true, "aboveLowerThreshold": true, "aboveUpperThreshold": false, "aboveBoundary": false, "hourlyLowerCount": 20, "hourlyUpperCount": 0, "hourlyBoundaryCount": 0}, {"year": 2013, "validHours": 8670.0, "aggregated": 253230.93844100088, "value": 29.207720696770576, "isValid": true, "aboveLowerThreshold": true, "aboveUpperThreshold": false, "aboveBoundary": false, "hourlyLowerCount": 27, "hourlyUpperCount": 0, "hourlyBoundaryCount": 0}, {"year": 2014, "validHours": 8477.0, "aggregated": 215012.794381, "value": 25.36425555986788, "isValid": true, "aboveLowerThreshold": false, "aboveUpperThreshold": false, "aboveBoundary": false, "hourlyLowerCount": 2, "hourlyUpperCount": 0, "hourlyBoundaryCount": 0}, {"year": 2015, "validHours": 8558.0, "aggregated": 188095.03465899936, "value": 21.978854248539303, "isValid": true, "aboveLowerThreshold": false, "aboveUpperThreshold": false, "aboveBoundary": false, "hourlyLowerCount": 0, "hourlyUpperCount": 0, "hourlyBoundaryCount": 0}, {"year": 2016, "validHours": 7947.0, "aggregated": 192508.98569899917, "value": 24.22410792739388, "isValid": true, "aboveLowerThreshold": false, "aboveUpperThreshold": false, "aboveBoundary": false, "hourlyLowerCount": 6, "hourlyUpperCount": 0, "hourlyBoundaryCount": 0}, {"year": 2017, "validHours": 7642.0, "aggregated": 165938.66933999988, "value": 21.714036814969887, "isValid": true, "aboveLowerThreshold": false, "aboveUpperThreshold": false, "aboveBoundary": false, "hourlyLowerCount": 2, "hourlyUpperCount": 0, "hourlyBoundaryCount": 0}, {"year": 2018, "validHours": 8023.0, "aggregated": 189115.3426809999, "value": 23.571649343263104, "isValid": true, "aboveLowerThreshold": false, "aboveUpperThreshold": false, "aboveBoundary": false, "hourlyLowerCount": 6, "hourlyUpperCount": 0, "hourlyBoundaryCount": 0}, {"year": 2019, "validHours": 7229.0, "aggregated": 143216.61007000034, "value": 19.811399926684235, "isValid": false, "aboveLowerThreshold": false, "aboveUpperThreshold": false, "aboveBoundary": false, "hourlyLowerCount": 10, "hourlyUpperCount": 0, "hourlyBoundaryCount": 0}, {"year": 2020, "validHours": 6774.0, "aggregated": 78744.82237999978, "value": 11.62456781517564, "isValid": false, "aboveLowerThreshold": false, "aboveUpperThreshold": false, "aboveBoundary": false, "hourlyLowerCount": 0, "hourlyUpperCount": 0, "hourlyBoundaryCount": 0}]}, {"component": "PM10", "unit": "\u00b5g/m\u00b3", "values": [{"year": 2012, "validHours": 8742.0, "aggregated": 188679.26000000027, "value": 21.58307709906203, "isValid": true, "aboveLowerThreshold": true, "aboveUpperThreshold": false, "aboveBoundary": false, "dailyLowerCount": 93, "dailyUpperCount": 51, "dailyBoundaryCount": 19}, {"year": 2013, "validHours": 8620.0, "aggregated": 178379.9600000003, "value": 20.693730858468715, "isValid": true, "aboveLowerThreshold": true, "aboveUpperThreshold": false, "aboveBoundary": false, "dailyLowerCount": 90, "dailyUpperCount": 35, "dailyBoundaryCount": 8}, {"year": 2014, "validHours": 8702.0, "aggregated": 180413.93240500047, "value": 20.7324675252816, "isValid": true, "aboveLowerThreshold": true, "aboveUpperThreshold": false, "aboveBoundary": false, "dailyLowerCount": 88, "dailyUpperCount": 27, "dailyBoundaryCount": 7}, {"year": 2015, "validHours": 8305.0, "aggregated": 117781.1304800001, "value": 14.181954302227584, "isValid": true, "aboveLowerThreshold": false, "aboveUpperThreshold": false, "aboveBoundary": false, "dailyLowerCount": 23, "dailyUpperCount": 7, "dailyBoundaryCount": 1}, {"year": 2016, "validHours": 8443.0, "aggregated": 109358.23399000001, "value": 12.952532747838447, "isValid": true, "aboveLowerThreshold": false, "aboveUpperThreshold": false, "aboveBoundary": false, "dailyLowerCount": 23, "dailyUpperCount": 5, "dailyBoundaryCount": 3}, {"year": 2017, "validHours": 8397.0, "aggregated": 101422.49714599976, "value": 12.078420524711177, "isValid": true, "aboveLowerThreshold": false, "aboveUpperThreshold": false, "aboveBoundary": false, "dailyLowerCount": 22, "dailyUpperCount": 7, "dailyBoundaryCount": 2}, {"year": 2018, "validHours": 8485.0, "aggregated": 104086.92061400003, "value": 12.26716801579258, "isValid": true, "aboveLowerThreshold": false, "aboveUpperThreshold": false, "aboveBoundary": false, "dailyLowerCount": 25, "dailyUpperCount": 7, "dailyBoundaryCount": 0}, {"year": 2019, "validHours": 7804.0, "aggregated": 82756.34045300029, "value": 10.604349109815516, "isValid": true, "aboveLowerThreshold": false, "aboveUpperThreshold": false, "aboveBoundary": false, "dailyLowerCount": 19, "dailyUpperCount": 3, "dailyBoundaryCount": 2}, {"year": 2020, "validHours": 6698.0, "aggregated": 62039.324164000136, "value": 9.262365506718444, "isValid": false, "aboveLowerThreshold": false, "aboveUpperThreshold": false, "aboveBoundary": false, "dailyLowerCount": 6, "dailyUpperCount": 2, "dailyBoundaryCount": 2}]}]}